oxide-0.1.0.dist-info/METADATA
oxide-0.1.0.dist-info/WHEEL
oxide-0.1.0.dist-info/license_files/LICENSE
oxide/oxide.pyi
oxide/__init__.py
oxide/oxide.cpython-39-x86_64-linux-gnu.so
oxide-0.1.0.dist-info/RECORD
